librepos/__init__.py
librepos/config.py
librepos/extensions.py
librepos/manage.py
librepos/router.py
librepos/seeds.py
librepos/auth/__init__.py
librepos/auth/decorators.py
librepos/auth/forms.py
librepos/auth/repository.py
librepos/auth/routes.py
librepos/auth/service.py
librepos/auth/templates/auth/login.html
librepos/main/__init__.py
librepos/main/routes.py
librepos/main/templates/main/settings.html
librepos/menu/__init__.py
librepos/menu/forms.py
librepos/menu/repository.py
librepos/menu/routes.py
librepos/menu/service.py
librepos/menu/templates/menu/get_category.html
librepos/menu/templates/menu/get_group.html
librepos/menu/templates/menu/get_item.html
librepos/menu/templates/menu/htmx_groups.html
librepos/menu/templates/menu/htmx_items.html
librepos/menu/templates/menu/hx_categories.html
librepos/menu/templates/menu/list_categories.html
librepos/menu/templates/menu/list_groups.html
librepos/menu/templates/menu/list_items.html
librepos/models/__init__.py
librepos/models/menu_categories.py
librepos/models/menu_groups.py
librepos/models/menu_items.py
librepos/models/permissions.py
librepos/models/policies.py
librepos/models/policy_permissions.py
librepos/models/role_policies.py
librepos/models/roles.py
librepos/models/shop_order_items.py
librepos/models/shop_orders.py
librepos/models/users.py
librepos/order/__init__.py
librepos/order/forms.py
librepos/order/repository.py
librepos/order/routes.py
librepos/order/service.py
librepos/order/templates/order/_sidenav.html
librepos/order/templates/order/get_order.html
librepos/order/templates/order/list_orders.html
librepos/ui/static/manifest.json
librepos/ui/static/css/override.css
librepos/ui/static/css/override.min.css
librepos/ui/static/css/style.css
librepos/ui/static/css/style.min.css
librepos/ui/static/css/theme.css
librepos/ui/static/css/theme.min.css
librepos/ui/static/fonts/flUhRq6tzZclQEJ-Vdg-IuiaDsNc.woff2
librepos/ui/static/images/default_female_user.png
librepos/ui/static/images/default_male_user.png
librepos-1.0.0.dev2.dist-info/METADATA
librepos-1.0.0.dev2.dist-info/WHEEL
librepos-1.0.0.dev2.dist-info/licenses/LICENSE
librepos-1.0.0.dev2.dist-info/RECORD
